kbrainsdk/__init__.py
kbrainsdk/admin.py
kbrainsdk/ai.py
kbrainsdk/api.py
kbrainsdk/apibase.py
kbrainsdk/azure_models/__init__.py
kbrainsdk/azure_models/model.py
kbrainsdk/datasets.py
kbrainsdk/encryption.py
kbrainsdk/events.py
kbrainsdk/ingest.py
kbrainsdk/llms.py
kbrainsdk/security/__init__.py
kbrainsdk/security/azure_authentication.py
kbrainsdk/security/bearer.py
kbrainsdk/signalr.py
kbrainsdk/users.py
kbrainsdk/validation/__init__.py
kbrainsdk/validation/admin.py
kbrainsdk/validation/ai.py
kbrainsdk/validation/common.py
kbrainsdk/validation/datasets.py
kbrainsdk/validation/events.py
kbrainsdk/validation/ingest.py
kbrainsdk/validation/llms.py
kbrainsdk/validation/signalr.py
kbrainsdk/validation/users.py
kbrainsdk-0.23.4.dist-info/METADATA
kbrainsdk-0.23.4.dist-info/WHEEL
kbrainsdk-0.23.4.dist-info/RECORD
