Metadata-Version: 2.1
Name: kbrainsdk
Version: 0.23.4
Summary: SDK for using KBRaiN tools
License: unlicensed
Author: Daniel E Fredriksen
Author-email: daniel.fredriksen@us.kbr.com
Requires-Python: >=3.8.1,<4.0.0
Classifier: License :: Other/Proprietary License
Classifier: Programming Language :: Python :: 3
Classifier: Programming Language :: Python :: 3.9
Classifier: Programming Language :: Python :: 3.10
Classifier: Programming Language :: Python :: 3.11
Classifier: Programming Language :: Python :: 3.12
Requires-Dist: cryptography (>=43.0.1,<44.0.0)
Requires-Dist: ecdsa (>=0.18.0,<0.19.0)
Requires-Dist: pandas (>=1.3.3,<2.0.0)
Requires-Dist: pyasn1 (>=0.5.1,<0.6.0)
Requires-Dist: python-dotenv (>=1.0.0,<2.0.0)
Requires-Dist: python-jose (>=3.3.0,<4.0.0)
Requires-Dist: requests (>=2.31.0,<3.0.0)
Requires-Dist: rsa (>=4.9,<5.0)
